{
  "generated_at_hkt": "2026-03-01T11:18:11.242176+08:00",
  "target_date_hkt": "2026-02-28",
  "source": "HKEX Application Proof / PHIP page (scraped by Playwright)",
  "count": 0,
  "items": [],
  "message": "No new HKEX AP postings found for the previous Hong Kong calendar day.",
  "debug": {
    "raw_row_count": 3374,
    "parsed_record_count": 763,
    "doc_type_distribution": {
      "AP": 762,
      "PHIP": 1
    },
    "top_dates": {
      "2026-01-30": 30,
      "2025-09-29": 26,
      "2025-09-30": 22,
      "2026-01-26": 20,
      "2026-02-27": 19,
      "2025-10-31": 19,
      "2026-01-16": 18,
      "2025-09-26": 18,
      "2026-02-13": 17,
      "2026-01-12": 15
    },
    "debug_dir": "data/debug"
  }
}